setup.py
phlawg/__init__.py
phlawg/config.py
phlawg.egg-info/PKG-INFO
phlawg.egg-info/SOURCES.txt
phlawg.egg-info/dependency_links.txt
phlawg.egg-info/requires.txt
phlawg.egg-info/top_level.txt
phlawg/test/__init__.py
phlawg/test/environmental_config_test.py
phlawg/test/logger_name_test.py
phlawg/test/metric_logger_test.py