Metadata-Version: 1.1
Name: phlawg
Version: 0.3.0
Summary: python logging utilities for transmitting metrics via log streams
Home-page: https://github.com/ethanrowe/python-phlawg
Author: Ethan Rowe
Author-email: ethan@the-rowes.com
License: MIT
Keywords: metrics logging configuration setup
Platform: UNKNOWN
Classifier: Development Status :: 3 - Alpha
Classifier: Intended Audience :: Developers
Classifier: Intended Audience :: System Administrators
Classifier: License :: OSI Approved :: MIT License
Classifier: Operating System :: OS Independent
Classifier: Programming Language :: Python :: 2.6
Classifier: Programming Language :: Python :: 2.7
Classifier: Programming Language :: Python :: 3.4
Classifier: Topic :: Utilities
